sparkle_hypothesis/__init__.py
sparkle_hypothesis/hypothesis_test_case.py
sparkle_hypothesis/pyspark_profile.py
sparkle_hypothesis/save_data_frames.py
sparkle_hypothesis/utils.py
sparkle_hypothesis-1.4.0.dist-info/LICENSE
sparkle_hypothesis-1.4.0.dist-info/WHEEL
sparkle_hypothesis-1.4.0.dist-info/METADATA
sparkle_hypothesis-1.4.0.dist-info/RECORD
