Metadata-Version: 2.1
Name: sparkle-hypothesis
Version: 1.4.0
Summary: Use the power of hypothesis property based testing in PySpark tests
Home-page: https://github.com/machielg/sparkle-hypothesis/
License: GPL-3.0-or-later
Author: Machiel Keizer Groeneveld
Author-email: machielg@gmail.com
Requires-Python: >=3.7.1,<4
Classifier: Environment :: Console
Classifier: Framework :: Hypothesis
Classifier: License :: OSI Approved :: GNU General Public License v3 or later (GPLv3+)
Classifier: Programming Language :: Python :: 3
Classifier: Programming Language :: Python :: 3.10
Classifier: Programming Language :: Python :: 3.7
Classifier: Programming Language :: Python :: 3.8
Classifier: Programming Language :: Python :: 3.9
Classifier: Topic :: Software Development :: Testing
Requires-Dist: hypothesis (>=6.42.2,<7.0.0)
Requires-Dist: sparkle-test (>=1.2.0,<2.0.0)
Project-URL: Repository, https://github.com/machielg/sparkle-hypothesis/
